{
  "project_info": {
    "project_number": "1063542947486",
    "firebase_url": "https://babyneeds-147308.firebaseio.com",
    "project_id": "babyneeds-147308",
    "storage_bucket": "babyneeds-147308.appspot.com"
  },
  "client": [
    {
      "client_info": {
        "mobilesdk_app_id": "1:1063542947486:android:5f45a68b42d179cd",
        "android_client_info": {
          "package_name": "com.maks.babyneeds"
        }
      },
      "oauth_client": [
        {
          "client_id": "1063542947486-bhk1m7ndv450p4mkblrrso8300ckg94n.apps.googleusercontent.com",
          "client_type": 1,
          "android_info": {
            "package_name": "com.maks.babyneeds",
            "certificate_hash": "d2c8763d68a25a20ab4244a456ba4798a925d2b2"
          }
        },
        {
          "client_id": "1063542947486-1k84qtg1vq3sh1nc6d4kskr99u9i4lko.apps.googleusercontent.com",
          "client_type": 3
        }
      ],
      "api_key": [
        {
          "current_key": "AIzaSyBgiPmo69UWVuuSVMmftO0vKjk86hZycSg"
        }
      ],
      "services": {
        "analytics_service": {
          "status": 1
        },
        "appinvite_service": {
          "status": 2,
          "other_platform_oauth_client": [
            {
              "client_id": "1063542947486-1k84qtg1vq3sh1nc6d4kskr99u9i4lko.apps.googleusercontent.com",
              "client_type": 3
            }
          ]
        },
        "ads_service": {
          "status": 2
        }
      }
    },
    {
      "client_info": {
        "mobilesdk_app_id": "1:1063542947486:android:1bb3ab30df9d169a",
        "android_client_info": {
          "package_name": "com.maks.babyneeds1"
        }
      },
      "oauth_client": [
        {
          "client_id": "1063542947486-e43sbi6htjcp6ufdjp2cvpoerut7r56e.apps.googleusercontent.com",
          "client_type": 1,
          "android_info": {
            "package_name": "com.maks.babyneeds1",
            "certificate_hash": "d2c8763d68a25a20ab4244a456ba4798a925d2b2"
          }
        },
        {
          "client_id": "1063542947486-7s5rvjdlrenfhqndb1nmq6chpgg1chfr.apps.googleusercontent.com",
          "client_type": 1,
          "android_info": {
            "package_name": "com.maks.babyneeds1",
            "certificate_hash": "fb7039713543624af00395955953475457151bba"
          }
        },
        {
          "client_id": "1063542947486-1k84qtg1vq3sh1nc6d4kskr99u9i4lko.apps.googleusercontent.com",
          "client_type": 3
        }
      ],
      "api_key": [
        {
          "current_key": "AIzaSyBgiPmo69UWVuuSVMmftO0vKjk86hZycSg"
        }
      ],
      "services": {
        "analytics_service": {
          "status": 1
        },
        "appinvite_service": {
          "status": 2,
          "other_platform_oauth_client": [
            {
              "client_id": "1063542947486-1k84qtg1vq3sh1nc6d4kskr99u9i4lko.apps.googleusercontent.com",
              "client_type": 3
            }
          ]
        },
        "ads_service": {
          "status": 2
        }
      }
    }
  ],
  "configuration_version": "1"
}